FENICE/FENICE.py
FENICE/__init__.py
FENICE/aggrefact.py
FENICE/claim_extractor/__init__.py
FENICE/claim_extractor/claim_extractor.py
FENICE/coreference_resolution/__init__.py
FENICE/coreference_resolution/coreference_resolution.py
FENICE/nli/__init__.py
FENICE/nli/nli_aligner.py
FENICE/utils/__init__.py
FENICE/utils/utils.py
metric/FENICE.py
metric/__init__.py
metric/aggrefact.py
metric/post_install.py
metric/claim_extractor/__init__.py
metric/claim_extractor/claim_extractor.py
metric/coreference_resolution/__init__.py
metric/coreference_resolution/coreference_resolution.py
metric/nli/__init__.py
metric/nli/nli_aligner.py
metric/utils/__init__.py
metric/utils/utils.py
FENICE-0.1.14.dist-info/LICENSE.txt
FENICE-0.1.14.dist-info/METADATA
FENICE-0.1.14.dist-info/WHEEL
FENICE-0.1.14.dist-info/top_level.txt
FENICE-0.1.14.dist-info/RECORD
