Metadata-Version: 2.1
Name: FENICE
Version: 0.1.14
Summary: This package contains the code to execute FENICE, a factuality-oriented metric for summarization
Home-page: https://github.com/Babelscape/FENICE
Author: Alessandro Scirè
Author-email: scire@diag.uniroma1.it
License: CC BY-NC-SA 4.0
Classifier: Programming Language :: Python :: 3
Classifier: Operating System :: OS Independent
Requires-Python: >=3.6
License-File: LICENSE.txt
Requires-Dist: numpy
Requires-Dist: torch
Requires-Dist: tqdm
Requires-Dist: spacy ==3.7.4
Requires-Dist: fastcoref ==2.1.6
Requires-Dist: transformers ~=4.38.2
Requires-Dist: sentencepiece ==0.2.0
Requires-Dist: scikit-learn ==1.5.0
